AUTHORS
CHANGELOG
CONTRIBUTING.rst
LICENSE
MANIFEST.in
README.rst
VERSION
setup.cfg
setup.py
pydocusign/.api.py.un~
pydocusign/.client.py.swp
pydocusign/.client.py.un~
pydocusign/.models.py.un~
pydocusign/.parser.py.un~
pydocusign/.test.py.un~
pydocusign/__init__.py
pydocusign/api.py
pydocusign/client.py
pydocusign/exceptions.py
pydocusign/models.py
pydocusign/parser.py
pydocusign/test.py
pydocusign.egg-info/PKG-INFO
pydocusign.egg-info/SOURCES.txt
pydocusign.egg-info/dependency_links.txt
pydocusign.egg-info/not-zip-safe
pydocusign.egg-info/requires.txt
pydocusign.egg-info/top_level.txt
pydocusign/templates/callback.xml