Metadata-Version: 1.1
Name: pydocusign
Version: 1.1
Summary: Python client for DocuSign signature SAAS platform.
Home-page: https://pydocusign.readthedocs.io/
Author: Benoît Bryon
Author-email: novafloss@people-doc.com
License: BSD
Platform: UNKNOWN
Classifier: Development Status :: 5 - Production/Stable
Classifier: License :: OSI Approved :: BSD License
Classifier: Programming Language :: Python :: 2.7
Classifier: Programming Language :: Python :: 3.3
Classifier: Programming Language :: Python :: 3.4
Classifier: Programming Language :: Python :: 3.5
